{
    "list": [
        {
            "date": "2023-06-01T00:07:20.267Z",
            "title": "Electron 25.0.0 | Electron",
            "url": "https://www.electronjs.org/blog/electron-25-0",
            "content": "Electron 25.0.0リリース。\nChromium 114、Node.js 18.15.0、V8 11.4へアップデート。\nChromiumのネットワークスタックを使った`net.fetch` APIの追加、`protocol.handle` APIの追加。\n`protocol.{register,intercept}{Buffer,String,Stream,File,Http}Protocol` APIの非推奨化など",
            "tags": [
                "Electron",
                "ReleaseNote"
            ],
            "relatedLinks": []
        },
        {
            "date": "2023-06-01T02:10:12.320Z",
            "title": "Release sveltejs@4.0.0-next.0 · sveltejs/svelte",
            "url": "https://github.com/sveltejs/svelte/releases/tag/svelte%404.0.0-next.0",
            "content": "Svelte 4.0.0-next.0リリース。\nNode.js 14のサポート終了、webpack 4のサポート終了、パッケージサイズの改善など",
            "tags": [
                "Svelte",
                "ReleaseNote"
            ],
            "relatedLinks": []
        },
        {
            "date": "2023-06-01T02:21:22.791Z",
            "title": "React Handbook",
            "url": "https://reacthandbook.dev/",
            "content": "Reactハンドブック。\nReactでのアプリケーション開発についてのガイド",
            "tags": [
                "React",
                "document"
            ],
            "relatedLinks": []
        },
        {
            "date": "2023-06-01T02:50:48.059Z",
            "title": "300ms Faster: Reducing Wikipedia's Total Blocking Time",
            "url": "https://www.nray.dev/blog/300ms-faster-reducing-wikipedias-total-blocking-time/",
            "content": "WikipediaのTBTのパフォーマンス改善について。\n不要なJavaScriptの削除、event delegationを使った処理の最適化について",
            "tags": [
                "performance",
                "article"
            ],
            "relatedLinks": []
        }
    ]
}
