{"list":[{"title":"開発者のための WebKit (“WebKit for Developers” 日本語訳)","url":"http://myakura.github.com/n/webkit4devs.html","content":"WebKitがどういう構成をしているか、WebKit portとは何か、どの部分が共通なのか、JavaScriptのバインディング、Operaが採用するChromium、WebKit Nightlyとは何か について書かれている","tags":["webkit","document","翻訳"]},{"title":"vladikoff/grunt-devtools · GitHub","url":"https://github.com/vladikoff/grunt-devtools","content":"Chrome Dev Tools上にGruntタスクへアクセスできるタブを追加するChrome拡張","tags":["Chrome","node.js","Extension"]},{"title":"SlowmoJS","url":"http://toolness.github.com/slowmo-js/","content":"JavaScriptのコードがどのような順番で実行されているかをステップ毎に表示して、その時評価されてる内容も見られるツール","tags":["javascript","Tools"]},{"title":"JavaScript Testing with Jasmine - O'Reilly Media","url":"http://shop.oreilly.com/product/0636920028277.do","content":"2013年4月発売\nJasmineでのテストについての短めの書籍","tags":["javascript","jasmine","testing","book"]},{"title":"jQueryUI 日本語リファレンス | js STUDIO","url":"http://js.studio-kingdom.com/jqueryui","content":"jQuery UI日本語リファレンス","tags":["jQuery","UI","翻訳","リファレンス"]},{"title":"jQuery Hotshot | Packt Publishing","url":"http://www.packtpub.com/jquery-hotshot/book","content":"2013年4月発売\njQuery 1.9, jQuery plugin, jQuery UI、 jQuery Mobileについての書籍\n","tags":["jQuery","book"]},{"title":"Learning JavaScriptMVC | Packt Publishing","url":"http://www.packtpub.com/building-javasript-web-applications-using-javascriptmvc/book","content":"2013年3月発売\nJavaScriptMVCについての短めの書籍\nQUnitを使ったテストやCIについて、MVCでウェブアプリケーションを作ってデプロイする所まで","tags":["javascript","MVC","book"]},{"title":"WebReflection/dom4 · GitHub","url":"https://github.com/WebReflection/dom4","content":"DOM4のprepend/appnd/before/after/replace/removeのpolyfill実装ライブライ","tags":["javascript","DOM","library"]},{"title":"NetBeans IDE 7.3 Release Information","url":"http://netbeans.org/community/releases/73/index.html","content":"NetBeans 7.3リリース.\nウェブアプリの新規作成テンプレ、JsTDを使ったテスト統合、内部ブラウザとCSSエディタ、Chrome拡張と連携したNetBeans上からJavaScriptデバッガを使えるように、REST client、JavaScriptエディタの改善","tags":["NetBeans","HTML","javascript","ReleaseNote"]},{"title":"NetBeans 7.3が出ました！ | Work Tool Smith [ワークツールスミス]","url":"http://worktoolsmith.com/2013/03/netbeans-7-3%e3%81%8c%e5%87%ba%e3%81%be%e3%81%97%e3%81%9f%ef%bc%81/","content":"NetBeans 7.3のChromeを使ったJavaScriptデバッガについて","tags":["NetBeans","Chrome"]},{"title":"jQuery 2.0 Beta 2 Released | Official jQuery Blog","url":"http://blog.jquery.com/2013/03/01/jquery-2-0-beta-2-released/","content":"jQuery 2.0 Beta 2 リリース\n.data()が再実装、querySelectorAllと matchesSelectorベースの小さなセレクタエンジンが追加された、カスタムビルドの追加","tags":["jQuery","ReleaseNote"]},{"title":"jsFiddleを使ってJavaScriptのテストを簡単に動かせるテンプレートサイトを作りました | Web scratch","url":"http://efcl.info/2013/0303/res3214/","content":"クリックするとjsFiddleでテストが書ける状態にするテンプレート.\nもっとテストを気軽に共有できるようになるといいな","tags":["javascript","testing","webservice"]},{"title":"PhoneGap | PhoneGap 2.5.0 Released!","url":"http://phonegap.com/blog/2013/02/28/pg-250-released/","content":"PhoneGap 2.5.0リリース","tags":["mobile","ReleaseNote"]},{"title":"BusterJSでテストに使うHTMLの設定と手動実行 - yaakaito.org","url":"http://yaakaito.github.com/blog/2013/03/01/buster-testbed-and-boot/","content":"Buster.JSでtestbed的な任意のHTMLでテストコードを動かすようにする設定について\nJsTDのようなHTML Docコメントを使ったfixtureのテストについても\nhttp://yaakaito.github.com/blog/2013/03/02/buster-html-doc-and-coffee/","tags":["BusterJS","testing"]},{"title":"testem + mocha on Travis-CI - ブラウザでのテストを自動化する - 四角革命前夜","url":"http://d.hatena.ne.jp/sasaplus1/20130301/1362145202","content":"mochaで動かしていたテストを、Travis CIでtestem経由で動かす設定について","tags":["javascript","testing","webservice"]},{"title":"Amazon: はじめてのNode.js -サーバーサイドJavaScriptでWebアプリを開発する- [大型本]: 松島 浩道","url":"http://www.amazon.co.jp/o/ASIN/4797370904/book042-22/ref=nosim","content":"2013年3月15日発売","tags":["node.js","サーバー","book"]},{"title":"Secrets of Awesome JavaScript API Design - Web Standards Sherpa","url":"http://webstandardssherpa.com/reviews/secrets-of-awesome-javascript-api-design/","content":"JavaScriptライブラリのAPIデザインについて.\nUnity & Harmony/balance/proportion/Emphasisの原則についてやどういう視点をもってAPIをデザインするかについて","tags":["javascript","API","design"]},{"title":"JavaScript Unit Testing | Packt Publishing","url":"http://www.packtpub.com/javascript-unit-testing/book","content":"JavaScriptのUnit Testについての書籍.\nJasmine, YUI Test, QUnit, JsTDがそれぞれ1章ずつ割かれてる","tags":["javascript","book"]},{"title":"Unit Testing Backbone.js Applications","url":"http://jspro.com/toolsandlibraries/unit-testing-backbone-js-applications/","content":"mochaとtestemを使ったテスト環境を作って、Backbone.jsを使ったTodoアプリをテストしながら作成していくチュートリアル","tags":["javascript","testing","tutorial"]},{"title":"JEPSO CI","url":"https://jepso-ci.com/","content":"Github hookを使ってpush時に実行できるブラウザのテストを実行するCIサービス.\nテスト実行ページ用のhtmlを用意して置いて実行させるシンプルな仕組み.\n","tags":["browser","testing","javascript","webservice"]},{"title":"Learning from the Brackets Open Source Code : Remote Synthesis","url":"http://remotesynthesis.com/post.cfm/learning-from-the-brackets-open-source-code","content":"Bracketsのコードから学べる事.\nクラス、継承とJSDoc、AMDとモジュール、Lintの設定、Jasmineによるテスト、Mustacheでのテンプレート、LESSを使ったCSS","tags":["javascript"]},{"title":"More CSS Secrets Another 10 things you may not know about CSS","url":"http://lea.verou.me/more-css-secrets/#intro","content":"CSS gradients/Transitions/animation/Hyphenation/ch unitなど最近のCSSの機能についてのスライド。\nスライドが実際に動くデモになってる","tags":["css","スライド"]},{"title":"Typeplate » A typographic starter kit encouraging great type on the Web","url":"http://typeplate.com/#stats-tabs","content":"typographic starter kit.\nSass/Lessなどで用意されてる","tags":["css","Sass"]},{"title":"CoffeeScript","url":"http://coffeescript.org","content":"CoffeeScript 1.6.1リリース\nsource mapsのサポート、bug fix","tags":["CoffeeScript","ReleaseNote"]},{"title":"mir.aculo.us JavaScript with Thomas Fuchs » Blog Archive » Zepto 1.0","url":"http://mir.aculo.us/2013/03/04/zepto-1-0/","content":"jQuery互換のAPIを持つ Zepto.js 1.0 リリース","tags":["javascript","jQuery","library","ReleaseNote"]},{"title":"Bootstrap 2.3.1 released · Bootstrap Blog","url":"http://blog.getbootstrap.com/2013/03/01/bootstrap-2-3-1-released/","content":"Bootstrap 2.3.1リリース\n2.3系が2.xの最後で次は3.0を予定","tags":["css","ReleaseNote"]},{"title":"RequireJS 2.1.5 Released ~ James Burke","url":"http://jrburke.com/2013/03/03/requirejs-2.1.5-released/","content":"RequireJS 2.1.5リリース","tags":["AMD","library","ReleaseNote"]},{"title":"JSHint - JSHint 1.1.0 is out","url":"http://jshint.com/blog/2013-03-05/1-1-0/","content":"JSHint 1.1.0リリース.\nPhantomJSのサポートを追加、Google Closure Linterと互換をとるgclオプションの追加、unusedのチェック設定を追加","tags":["javascript","Tools","ReleaseNote"]},{"title":"Headless Functional Testing with Selenium and PhantomJS | Nettuts+","url":"http://net.tutsplus.com/tutorials/javascript-ajax/headless-functional-testing-with-selenium-and-phantomjs/","content":"PhantomJSとWebDriverとmochaを使って自動テスト","tags":["browser","testing"]},{"title":"Node v0.8.22 (Stable)","url":"http://blog.nodejs.org/2013/03/06/node-v0-8-22-stable/","content":"Node v0.8.22リリース","tags":["node.js","ReleaseNote"]},{"title":"Zepto.js ver1.0がリリースされました | 1000ch.net","url":"http://1000ch.net/2013/03/05/ZeptoIsReleased/","content":"Zepto.js 1.0の変更点について","tags":["jQuery","javascript","library","ReleaseNote"]},{"title":"Chromium Feature Dashboard","url":"http://www.chromestatus.com/features","content":"Chromiumの実装されてる機能のステータスや標準化の進行度、prefixの有無、他のブラウザに実装されたバージョン、参考ドキュメントなどをまとめてる表","tags":["Chrome","まとめ"]},{"title":"Flight入門","url":"http://www.slideshare.net/bs_yagi/flight-16990467","content":"FlightのAMDモジュールの使い方についてのスライド","tags":["twitter","javascript","スライド"]},{"title":"Testing Clientside JavaScript - Online Training Course for .NET Developers","url":"http://pluralsight.com/training/Courses/TableOfContents/testing-javascript","content":"有料のsubscriber向けだけど、QUnit,Jasmine,Mocha,モック,Jasmineのspy,Sinon.JS, Utilなどについてのオンライン講座","tags":["javascript","動画"]},{"title":"WebStorm 6.0 released: adds TypeScript, debugging with source maps, fresh UI and much more | WebStorm & PhpStorm Blog","url":"http://blog.jetbrains.com/webide/2013/03/webstorm-6-0-released-adds-typescript-debugging-with-source-maps-fresh-ui-and-much-more/","content":"WebStorm 6.0リリース.\n保存するごとにスクリプトを走らせられるFile Watcher、TypeScriptやCoffeeScript等のデバッグ連携、ビルドインのRESTクライアント、Google Closure Linterの追加など","tags":["WebStorm","ReleaseNote"]},{"title":"rawson.js - a camera raw previewer in javascript","url":"http://dev.tag.is/rawson.js/","content":"色々なカメラのraw画像をサポートしてるJavaScriptで書かれてるデコードを使った画像ビューアー","tags":["javascript","画像"]},{"title":"Using the Console - Chrome Developer Tools — Google Developers","url":"https://developers.google.com/chrome-developer-tools/docs/console","content":"Chrome Dev ToolsのConsole周りの解説\nConsole APIの解説","tags":["Chrome","デバック"]},{"title":"espadrine/aulx · GitHub","url":"https://github.com/espadrine/aulx","content":"JavaScriptで書かれたHTML/CSS/JavaScriptの自動補完ライブラリ\n静的解析、静的な型推論、動的解析","tags":["javascript","library"]},{"title":"Tern","url":"http://ternjs.net/","content":"自動補完、宣言元へのジャンプ、リファクタリング等の機能が入ったJavaScriptなエディタライブラリ.\nSpiderMonkey で使われてるアルゴリズムを元にした型推論をしていて、パーサーは同作者のAcornを使用。","tags":["javascript","library"]},{"title":"Writing Testable Frontend Javascript Part 2 – Refactor away anti-patterns | Shane Tomlinson","url":"https://shanetomlinson.com/2013/writing-testable-javascript-part-2-refactor-away-anti-patterns/","content":"テストしやすいJavaScript part2.\npart1でアンチパターンを解消して、今回はリファクタリングをしていく。\nモジュール化していきPublic APIを整理していく、イベントハンドラを関数に分ける(detachもしやすくなる)、DOM/XHRのモックなどについて","tags":["javascript","event","testing"]},{"title":"slightlyoff/DOMFuture · GitHub","url":"https://github.com/slightlyoff/DOMFuture","content":"DOMの非同期API(XHRやonloadなど)に対するPromiseのIDLと実装としてのPolyfill","tags":["DOM","event","javascript","google"]},{"title":"#FranceJS : Communauté française de promotion de JavaScript","url":"http://francejs.org/manifeste.html","content":"フランスのJavaScriptコミュニティ #FranceJS がオープンされた。\n短期的な目標としてフランスローカルのコミュニティの発展。先の目的としては非営利団体として活動できるようにすることが上げられてる。\nオープンで民主的であり、それらを円滑に進めるためにGithubやIRCやGoogle+等のコミュニケーションツールを用意してある。","tags":["javascript","community"]},{"title":"Scripted 0.4 - release notes","url":"http://scripted-editor.github.com/scripted/release_notes/0_4_0/scripted_0_4_0.html","content":"OrionのコードエディタベースのScripted 0.4リリース。\nコードテンプレート、JSdocツールチップ、Zencoding、AMDモジュールを使ったプラグイン機構\n","tags":["javascript","editor"]},{"title":"Node v0.10.0 (Stable)","url":"http://blog.nodejs.org/2013/03/11/node-v0-10-0-stable/","content":"Node v0.10.0リリース(stable release)\n\n","tags":["node.js","ReleaseNote"]},{"title":"Yeti 0.2.18 released","url":"http://www.yeti.cx/blog/2013/03/yeti-0-2-18-released/","content":"Yeti 0.2.18 リリース.\nキャプチャーページでのsmart timeouts、parallel browser testingのためのリファクタリング","tags":["javascript","testing","ReleaseNote"]},{"title":"プライベートメソッドのユニットテストは書かないもの？ - QA@IT","url":"http://qa.atmarkit.co.jp/q/2784","content":"プライベートメソッドのテストはどうするべきなのかという質問に対する対処法","tags":["javascript","testing","program"]},{"title":"Amazon: Enterprise Web Development: Building HTML5 Applications: From Desktop to Mobile [Paperback]: Yakov Fain, Victor Rasputnis, Anatole Tartakovsky, Viktor Gamov","url":"http://www.amazon.com/o/ASIN/1449356818/book042-22/ref=nosim","content":"2013年9月22日発売\nエンタープライズのウェブアプリケーションについての書籍","tags":["book","webservice"]},{"title":"Announcing YUI 3.9.0 - YUI Blog","url":"http://www.yuiblog.com/blog/2013/03/13/announcing-yui-3-9-0/","content":"YUI 3.9.0リリース.\n","tags":["javascript","library","ReleaseNote"]},{"title":"Web Audio API - O'Reilly Media","url":"http://shop.oreilly.com/product/0636920025948.do","content":"WebAudioAPIについての書籍","tags":["music","WebAPI","book"]},{"title":"jQuery UI 1.10.2 | jQuery UI Blog","url":"http://blog.jqueryui.com/2013/03/jquery-ui-1-10-2/","content":"jQuery UI 1.10.2リリース","tags":["jQuery","UI","ReleaseNote"]},{"title":"Yeti 0.2.19 released","url":"http://www.yeti.cx/blog/2013/03/yeti-0-2-19-released/","content":"Yeti 0.2.19リリース\n uncaught errorsの改善、WebDriver CLIオプションの追加","tags":["javascript","testing","ReleaseNote"]},{"title":"Grunt 0.4.1 released - Grunt: The JavaScript Task Runner","url":"http://gruntjs.com/blog/2013-03-13-grunt-0.4.1-released","content":"Grunt 0.4.1 リリース","tags":["javascript","Tools","ReleaseNote"]},{"title":"Daniel Davis - List of JavaScript charting libraries","url":"http://my.opera.com/tagawa/blog/list-of-javascript-charting-libraries","content":"JavaScriptのグラフ系ライブラリのまとめ","tags":["javascript","グラフ","library","まとめ"]},{"title":"JS Git by Tim Caswell — Kickstarter","url":"http://www.kickstarter.com/projects/creationix/js-git","content":"JavaScriptのGit実装を作るKickstarter.\nChromebookのような環境でも使えるGitを","tags":["javascript","git","library"]},{"title":"Aptana Studio Beginner's Guide | Packt Publishing","url":"http://www.packtpub.com/aptana-studio-3-integrated-development-environment-beginners-guide/book","content":"Aptana Studioについての書籍","tags":["javascript","IDE","php"]},{"title":"Run server-side code and discover APIs in your browser","url":"http://runnable.com/","content":"node.jsをブラウザ上で書いて実行できるウェブサービス","tags":["node.js","webservice"]},{"title":"Formula.js","url":"http://stoic.com/formula/index.html","content":"Excel関数(ExcelとGoogle SpreadSheets)のJavaScript実装ライブラリ","tags":["javascript","library"]},{"title":"Dirty Markup · Tidy and Beautify your HTML, CSS, and JavaScript code","url":"http://www.dirtymarkup.com/","content":"HTML/CSS/JavaScriptを整形ツール\nWord HTMLを最適化するオプションもあったりする","tags":["HTML","css","javascript","Tools"]},{"title":"QUnit で ECMAScript 6th Compatibility Test を書いてみた - hogehoge @teramako","url":"http://d.hatena.ne.jp/teramako/20130317/p1","content":"ECMAScript compatibility tableのQunitで実行できるテストケース","tags":["javascript","testing","ECMA"]},{"title":"Refactoring setInterval-based polling - Adventures in JavaScript Development","url":"http://rmurphey.com/blog/2013/02/04/refactoring-setInterval-polling/","content":"setTimeIntervalで単純に回してた処理を、ちゃんと成否を確認してからsetTimeoutで回すように変更する方法やPromiseを使った方法へのリファクタリングについて","tags":["javascript","Tips"]},{"title":"Firefox上のFlash Playerで、保護モードが有効でもIMEが利用できるようにする方法 - WebStudio","url":"http://www.d-toybox.com/studio/weblog/show.php?mode=single;id=2013031500","content":"wmodeを使って保護モードでもIMEが利用できるように回避する方法","tags":["flash","firefox","IME"]},{"title":"非同期プログラミングを驚きのシンプルさに (するかもしれない) Flow.js を公開しました。 - latest log","url":"http://uupaa.hatenablog.com/entry/2013/03/12/185555","content":"カウンタベースのフロー制御ライブラリ","tags":["javascript","library","スライド"]},{"title":"CSS Front-end Frameworks with comparison - By usabli.ca","url":"http://usablica.github.com/front-end-frameworks/compare.html?v=2.0","content":"CSSフレームワークの対応ブラウザとプラットフォーム、使用してる言語(Sass/Less)、ライセンスのまとめ","tags":["css","まとめ"]},{"title":"GoodBoyDigital/pixi.js · GitHub","url":"https://github.com/GoodBoyDigital/pixi.js","content":"WebGLを使った2Dレンダリングエンジン","tags":["javascript","canvas","WebGL"]},{"title":"JS: The Right Way","url":"http://jstherightway.com/","content":"JavaScriptのデザインパターンやツール、リソース、書籍等のまとめ","tags":["javascript","まとめ"]},{"title":"Touch And Mouse: Together Again For The First Time - HTML5 Rocks","url":"http://www.html5rocks.com/en/mobile/touchandmouse/","content":"touch/move/clickのイベントの順序.\nタッチイベントとマウスイベントどちらも対応することについて","tags":["javascript","DOM"]},{"title":"jQuery Mobile 1.3 最新情報","url":"http://www.slideshare.net/yoshikawa_t/jquery-mobileupdates","content":"jQuery Mobile 1.3のあたらしい機能などについてのスライド","tags":["jQuery","mobile","スライド"]},{"title":"Future of Firefox DevTools // by Paul Rouget","url":"http://paulrouget.com/e/devtoolsnext/","content":"Firefox DevToolsの未来の機能.\nエディタで編集したCSSをリアルタイムで反映するLive Edit/jsFiddleのような形態のエディタ/ネットワークパネル/CoffeeScript+SourceMapのサポート/repaint/アニメーションのデバッグ","tags":["firefox","デバック"]},{"title":"webstormの「Instant HTML/CSS editing」が凄い - miniapp","url":"http://miniapp.org/blog/2012/06/28/304/","content":"WebStormとかのLive Edit機能についての動画","tags":["WebStorm"]},{"title":"HTMLでDOCTYPE宣言はなぜ必要か？ | input*output","url":"http://inputxoutput.com/html-doctype/","content":"HTMLのDOCTYPE宣言が必要な歴史的な理由","tags":["HTML","歴史"]},{"title":"Karma - Changelog","url":"http://karma-runner.github.com/0.8/about/changelog.html","content":"testacular 改め Karma 0.8.0リリース。\n名前変えた経緯は以下参照 : \nhttps://github.com/karma-runner/karma/issues/376","tags":["javascript","testing","ReleaseNote"]},{"title":"Amazon: スラスラわかるJavaScript (Beginner’s Best Guide to Programmin) [単行本（ソフトカバー）]: 生形 可奈子","url":"http://www.amazon.co.jp/o/ASIN/4798125830/book042-22/ref=nosim","content":"プログラミング初心者向けのJavaScript本\nhttp://books.shoeisha.co.jp/book/b101804.html","tags":["javascript","book"]},{"title":"Manning: AngularJS in Action","url":"http://www.manning.com/bford/","content":"発売はFall 2013年予定\nAngularJSのAction本","tags":["AngularJS","javascript","book"]},{"title":"Backbone 1.0","url":"http://ashkenas.com/backbonejs-1.0/","content":"Backbone 1.0リリース","tags":["javascript","MVC","ReleaseNote"]},{"title":"Yeti 0.2.20 released - YUI Blog","url":"http://www.yuiblog.com/blog/2013/03/20/yeti-0-2-20-released/","content":"Yeti 0.2.20リリース。\n","tags":["javascript","testing","ReleaseNote"]},{"title":"Default Parameters in JavaScript","url":"http://designpepper.com/blog/drips/default-parameters-in-javascript","content":"JavaScriptでデフォルトパラメータを書く方法について。\njQueryとかでよく見るextendによる実装について","tags":["javascript"]},{"title":"Superhero.js","url":"http://superherojs.com/","content":"JavaScriptのよいリソースまとめ.\n学び方、管理方法、テスト、ツール、パフォーマンスとプロファイル、セキュリティ、ブラウザ内部、未来について等","tags":["javascript","links","まとめ"]},{"title":"RequireJSを活用したキャッシュ防止、A/Bテスト、画像事前読込など - eller's blog","url":"http://eller86.hatenablog.jp/entry/2013/03/20/004648","content":"RequireJSのTips集\nキャッシュの防止、A/Bテスト、画像の先読み、i18n","tags":["javascript","AMD","Tips"]},{"title":"Functional JavaScript - O'Reilly Media","url":"http://shop.oreilly.com/product/0636920028857.do","content":"2013年6月発売\n関数型JavaScriptについての書籍","tags":["javascript","book"]},{"title":"CI as a Service – ブラウザを使ったJavaScriptのテストをCIサービスで動かす方法のまとめ | Web scratch","url":"http://efcl.info/2013/0321/res3234/","content":"Travis CI、drone.io、BuildHive、Jepso CI のCIサービスを使ってJavaScriptのテストをする連携方法について","tags":["javascript","browser","testing","CI","webservice"]},{"title":"Node v0.10.1 (Stable)","url":"http://blog.nodejs.org/2013/03/21/node-v0-10-1-stable/","content":"Node v0.10.1 リリース","tags":["node.js","ReleaseNote"]},{"title":"Amazon: JavaScript ライブラリ実践活用〔厳選111〕 (Software Design plus) [大型本]: WINGSプロジェクト, 山田祥寛, 安西剛, 高江賢, 高野将","url":"http://www.amazon.co.jp/o/ASIN/4774156116/book042-22/ref=nosim","content":"2013年3月20日発売\nJavaScriptのUIライブラリ、モバイル向け、フレームワーク、テストライブラリなどについて扱う書籍","tags":["javascript","library","Tools","book"]},{"title":"Amazon.co.jp： JavaScript ライブラリ実践活用〔厳選111〕 (Software Design plus): WINGSプロジェクト: 本","url":"http://www.amazon.co.jp/o/ASIN/4774156116/book042-22/ref=nosim","content":"2013年3月20日発売 JavaScriptのUIライブラリ、モバイル向け、フレームワーク、テストライブラリなどについて扱う書籍\nPDF版もある\nhttps://gihyo.jp/dp/ebook/2013/978-4-7741-5647-7","tags":["javascript","library","Tools","book"]},{"title":"jQuery Mobile 1.3 - Das Kompendium mit 200 Seiten","url":"http://www.slideshare.net/plobacher/jquery-mobile-13-das-kompendium-mit-200-seiten","content":"jQuery Mobile 1.3の機能や変更点について詳しく書かれたスライド","tags":["jQuery","mobile","スライド"]},{"title":"Sublimewebinspector","url":"http://sokolovstas.github.com/SublimeWebInspector/","content":"SublimeText2からChrome Dev Toolsのremote debuggerと連携して、SublimeText2内にブレークポイントやコンソール、コードの評価などをできるようにするplguin","tags":["SublimeText2","Chrome"]},{"title":"","url":"http://sokra.github.com/source-map-visualization/","content":"SourceMapの対応関係を可視化して見られる","tags":["javascript"]},{"title":"Announcing jQuery Mobile 1.2.1 | jQuery Mobile","url":"http://jquerymobile.com/blog/2013/03/22/announcing-jquery-mobile-1-2-1/","content":"jQuery Mobile 1.2.1 のメンテナンスリリース","tags":["jQuery","mobile","ReleaseNote"]},{"title":"O'Reilly Chimera - A new interactive online learning platform (beta)","url":"http://chimera.labs.oreilly.com/books/1230000000545/","content":"TCP/HTTP、HTTP 2.0(SPDY)、WebRTC,WebSockets,Sever Sent Event, XHR、ブラウザ周りのネットワークパフォーマンスについてのベストプラクティスなどについて書籍","tags":["HTTP","book","browser"]},{"title":"クライアントサイドMVCには何が必須? - HAKOBE blog ♨","url":"http://hakobe932.hatenablog.com/entry/2013/03/22/010357","content":"依存を小さくクライアントサイドMVCと言われてる機能を実現するために、コンパクトなObserverパターンをベースとしたものについて。\nBackbone.js/Knockout.js/Lucid.JSでTodoを実装したサンプル","tags":["javascript","MVC","HTML"]},{"title":"jQuery×HTML5×CSS3を真面目に勉強（1）：パララックスエフェクトの基本 (1/4) - ＠IT","url":"http://www.atmarkit.co.jp/ait/articles/1303/28/news005.html","content":"パララックスエフェクトなサイトの作り方についてのチュートリアル","tags":["javascript","DOM","css"]},{"title":"cfv1984/Pomo · GitHub","url":"https://github.com/cfv1984/pomo","content":"GNU gettextのJavaScript実装\nPO/MOファイルを扱える","tags":["javascript","i18n","Tools"]},{"title":"Chart.js | HTML5 Charts for your website.","url":"http://www.chartjs.org/","content":"グラフライブラリ","tags":["グラフ","javascript","library"]},{"title":"segv/jss · GitHub","url":"https://github.com/segv/jss","content":"EmacsからWebkit Inspector / Firefox Dev Toolsにremote debug連携するelisp","tags":["emacs","browser","デバック"]},{"title":"maxogden/art-of-node · GitHub","url":"https://github.com/maxogden/art-of-node","content":"Node.jsについての紹介.\nアーキテクチャやモジュールなどについて","tags":["node.js","tutorial"]},{"title":"Open Web Platform Daily Digest","url":"http://daily.w3viewer.com/","content":"日刊でWebプラットフォームに関するニュースを書いてるサイト.","tags":["web","news"]},{"title":"Dependent Types for JavaScript","url":"http://www.infoq.com/presentations/Type-System-JavaScript","content":"JavaScript論文 - DJS(Dependent JavaScript) についての発表\nLogicなアプローチ/型コメント\nhttp://cseweb.ucsd.edu/~rchugh/research/nested/djs.pdf\nhttps://github.com/ravichugh/djs","tags":["javascript","PDF","スライド","動画"],"date":"2013-03-24T01:42:24.124Z"},{"title":"Debug in safari","url":"http://www.slideshare.net/html5j/debug-in-safari-17451632","content":"Safariの開発メニューについてのスライド\niOSのデバッグ","tags":["safari","デバック","スライド"],"date":"2013-03-24T10:16:45.606Z"},{"title":"Code smells in CSS | en.ja | Translated Articles for Front End Developers","url":"http://enja.studiomohawk.com/2013/03/24/code-smells-in-css/","content":"CSSの臭いについて\n筋な悪そうなCSS - スタイルの取り消し、マジックナンバー、セレクタの付け方、範囲がでかすぎるセレクタ、受動的な!importantやセレクタの命名をどう改善するかについて","tags":["css","document","翻訳"],"date":"2013-03-24T10:20:01.272Z"},{"title":"pazguille/jvent · GitHub","url":"https://github.com/pazguille/jvent","content":"Node.JSのEventEmitterをクライアントサイド向けにした感じのライブラリ","tags":["node.js","javascript","event","library"],"date":"2013-03-24T10:22:44.528Z"},{"title":"Domイベントの基礎から深淵まで","url":"http://www.slideshare.net/masayukinakano560/dom-17527671","content":"DOMイベントについてのスライド.\nキャプチャ/バブリングフェーズの解説、trusted/untrustedイベント/init*Eventでのイベントの作成、mousewheel、buttons、getModifierState()、IMEのみ確定文字列を検知できるCompositionEvent、.keyと.charについて","tags":["DOM","event","スライド"],"date":"2013-03-24T10:48:18.392Z"},{"title":"Michal Budzynski: JavaScript: The less known parts. Bitwise Operators.","url":"http://michalbe.blogspot.com/2013/03/javascript-less-known-parts-bitwise.html","content":"ビット演算について。\nXORswap(値の交換)の比較","tags":["JavaScript"],"date":"2013-03-25T06:48:45.490Z"},{"title":"Load Your Game Faster with AppCache - Learning Three.js","url":"http://learningthreejs.com/blog/2013/03/22/load-your-game-faster-with-appcache/","content":"Chrome Dev toolsからHARを取得して、それをAppChacheのマニフェストに変換する方法について","tags":["JavaScript","HTML5"],"date":"2013-03-26T14:07:49.974Z"},{"title":"DevTools Extensions For Web App Developers","url":"http://addyosmani.com/blog/devtools-extensions-for-webapp-developers/","content":"Chrome Dev Toolsの拡張機能紹介","tags":["Chrome","デバック","Extension"],"date":"2013-03-26T14:23:21.086Z"},{"title":"Amazon: The Definitive Guide to HTML5 WebSocket (Definitive Guide Apress) [Paperback]: Vanessa Wang, Visit Amazon's Vanessa Wang Page, search results, Learn about Author Central, Frank Salim, Visit Amazon's Frank Salim Page, search results, Learn about Author Central, Peter Moskovits, Visit Amazon's Peter Moskovits Page, search results, Learn about Author Central","url":"http://www.amazon.com/o/ASIN/1430247401/book042-22/ref=nosim","content":"WebSocket本","tags":["WebSocket","book"],"date":"2013-03-27T00:37:04.985Z"},{"title":"PhantomJS 1.9 Release Notes","url":"http://phantomjs.org/release-1.9.html","content":"PhantomJS 1.9リリース。\n1.xのラストリリース","tags":["webkit","browser","Tools","console"],"date":"2013-03-27T12:23:21.831Z"},{"title":"YUI 3.9.1 Released - YUI Blog","url":"http://www.yuiblog.com/blog/2013/03/27/yui-3-9-1-released/","content":"YUI 3.9.1リリース","tags":["JavaScript","library","ReleaseNote"],"date":"2013-03-28T04:35:08.558Z"},{"title":"google/traceur-compiler · GitHub","url":"https://github.com/google/traceur-compiler","content":"Traceur Compiler @ github","tags":["JavaScript","google","ECMA"],"date":"2013-03-29T00:22:47.401Z"},{"title":"Node v0.10.2 (Stable)","url":"http://blog.nodejs.org/2013/03/28/node-v0-10-2-stable/","content":"Node v0.10.2リリース","tags":["node.js","ReleaseNote"],"date":"2013-03-29T04:27:55.956Z"},{"title":"Michal Budzynski: JavaScript: The less known parts. Bitwise Operators.","url":"http://michalbe.blogspot.com/2013/03/javascript-less-known-parts-bitwise.html","content":"ビット演算について。 XORswap(値の交換)について。 最後のJSperfはdeleteのせいで差が出てるだけなので、 http://jsperf.com/binswapwars/7 の方を見る","tags":["JavaScript"],"date":"2013-03-29T16:56:02.744Z"},{"title":"DailyJS: Backbone.js Tutorial: Updates for 1.0, Clear Complete","url":"http://dailyjs.com/2013/03/28/backbone-tutorial-15/","content":"Backbone.js ver 1.0に対応したチュートリアル ","tags":["backbone.js","tutorial"],"date":"2013-03-30T07:02:12.125Z"},{"title":"Same-Origin Policy とは何なのか。 - 葉っぱ日記","url":"http://d.hatena.ne.jp/hasegawayosuke/20130330/p1","content":"SameOriginポリシーについての解説.\nXRH,Canvas,WebStorage,X-Frame-Options等のoriginを元にしたものと、\nCookie,HTTPAuth,document.domain等独自のポリシーによるものなどをのまとめ","tags":["HTTP","web","セキュリティ"],"date":"2013-03-30T08:27:18.701Z"},{"title":"searls - jasmine tactics screencast","url":"http://searls.testdouble.com/posts/2013-03-21-jasmine-tactics-screencast.html","content":"Backbone.jsで書いたWebアプリをJasmineを使ってテストしながらリファクタリングするスクリーンキャスト","tags":["jasmine","JavaScript","testing","動画"],"date":"2013-03-30T10:42:55.252Z"},{"title":"google/kratu · GitHub","url":"https://github.com/google/kratu","content":"CSV等からデータを読み込んで、JSONでデータの重みを定義して、それを元に整形やランキング付けした表を生成するJavaScriptライブラリ","tags":["JavaScript","library"],"date":"2013-03-30T11:02:02.123Z"},{"title":"Josh.js by sdether","url":"http://sdether.github.com/josh.js/index.html","content":"JavaScriptでシェルのような機能を提供するライブラリ。\nreadlineをサポートしていてbashライクな動作を作れる","tags":["JavaScript","console","library"],"date":"2013-03-30T11:05:08.660Z"},{"title":"Web Reflection: 5 Reasons You Should Avoid __proto__","url":"http://webreflection.blogspot.de/2013/03/5-reasons-you-should-avoid-proto.html","content":"__proto__ について。\nvar Dict = Object.create.bind(Object, null);\nvar dictionary = Dict();// とかES5を使った__proto__に関する面白い実装も載せてる","tags":["JavaScript","ECMA"],"date":"2013-03-30T11:37:12.936Z"},{"title":"What's The Point Of Promises?","url":"http://www.kendoui.com/blogs/teamblog/posts/13-03-28/what-is-the-point-of-promises.aspx","content":"CallbackとPromiseについて、非同期のピラミッド。 \nPromiseの役割、$.whenの並列実行、値を渡していく同期的なコードを見た目そのままに非同期を適応したりと面白い感じの内容","tags":["JavaScript"],"date":"2013-03-30T13:19:14.496Z"},{"title":"Introducing mqa.js — Andrée Hansson","url":"http://andreehansson.se/introducing-mqa-js/","content":"mediaqueryが有効になったタイミングに動作する処理を付けられるJavaScriptライブラリ.\nmatchMediaを使ってる","tags":["JavaScript","library","css"],"date":"2013-03-30T13:32:17.412Z"},{"title":"MarionetteJS v1.0 | ThoughtStream.new :derick_bailey","url":"http://lostechies.com/derickbailey/2013/03/25/marionettejs-v1-0-now-with-stickers/","content":"Backbone.jsを拡張したラッパーライブラリのmarionette 1.0リリース\nBackbone.js 1.0対応","tags":["backbone.js","library"],"date":"2013-03-30T13:38:37.305Z"},{"title":"Code School - Discover DevTools","url":"http://discover-devtools.codeschool.com/","content":"Chrome Dev Toolsの動画チュートリアル。\n実際にDev Toolsを動かす演習問題もあってかなり丁寧な作り","tags":["Chrome","デバック","動画","tutorial"],"date":"2013-03-30T14:37:31.759Z"},{"title":"外部 script の document.write が何もしない条件などについて - ひだまりソケットは壊れない","url":"http://vividcode.hatenablog.com/entry/html/scripting-timing","content":"DOM操作で追加されたScriptの実行タイミングについて仕様から","tags":["JavaScript","DOM"],"date":"2013-03-30T17:00:39.534Z"},{"title":"FirefoxでJITコンパイルの「正しさ」を担保する”Invalidation” | ψ（プサイ）の興味関心空間","url":"http://ledyba.org/2013/02/27181531.php","content":"JITコンパイラIonMonkeyでのInvalidationの仕組み、型推論とJIT。\nJITコードを生成するInvalidationとGuardingの仕組みの違いの解説。","tags":["JavaScript"],"date":"2013-03-31T08:43:47.435Z"}]}