{
    "list": [
        {
            "date": "2019-11-01T07:47:40.811Z",
            "title": "React Conf 2019 - YouTube",
            "url": "https://www.youtube.com/playlist?list=PLPxbbTqCLbGHPxZpw4xj_Wwg8-fdNxJRh",
            "content": "React Conf 2019の動画一覧",
            "tags": [
                "React",
                "video"
            ],
            "relatedLinks": [
                {
                    "title": "React Conf 2019 - Fall 2019 in Lake Las Vegas, Nevada",
                    "url": "https://conf.reactjs.org/"
                }
            ]
        },
        {
            "date": "2019-11-01T12:32:54.352Z",
            "title": "SameSite cookie recipes",
            "url": "https://web.dev/samesite-cookie-recipes/",
            "content": "SameSite Cookiesへの対応方法について。\nSameSite=Noneに対応していないUAの対策として、LegacyなCookieととSameSite属性をつけたCookieを両方渡すパターンについてなど",
            "tags": [
                "browser",
                "security"
            ],
            "relatedLinks": []
        },
        {
            "date": "2019-11-03T13:48:34.205Z",
            "title": "mikro-orm/mikro-orm: TypeScript ORM for Node.js based on Data Mapper, Unit of Work and Identity Map patterns. Supports MongoDB, MySQL, MariaDB, PostgreSQL and SQLite databases.",
            "url": "https://github.com/mikro-orm/mikro-orm",
            "content": "TypeScriptで書かれたMongoDB、MySQL、PostgreSQLなどのORMマッパーライブラリ",
            "tags": [
                "TypeScript",
                "rnode",
                "library",
                "MySQL",
                "MongoDB"
            ],
            "relatedLinks": []
        },
        {
            "date": "2019-11-04T07:37:29.845Z",
            "title": "ReactHooksでvideoを乗りこなす - Speaker Deck",
            "url": "https://speakerdeck.com/narirou/reacthookstevideowocheng-rikonasu",
            "content": "React Hooksを使ってVideoプレイヤーを作成することについてのスライド。\n`<video>`要素の持つ複雑なステート管理、更新頻度に合わせたステートの分離、React Hooksの利用についてなど",
            "tags": [
                "React",
                "video",
                "slide"
            ],
            "relatedLinks": []
        },
        {
            "date": "2019-11-04T11:50:26.150Z",
            "title": "kroitor/asciichart: Nice-looking lightweight console ASCII line charts ╭┈╯ for NodeJS, browsers and terminal, no dependencies",
            "url": "https://github.com/kroitor/asciichart",
            "content": "コンソールでAscii線グラフを描画するライブラリ",
            "tags": [
                "JavaScript",
                "graphic",
                "library",
                "console"
            ],
            "relatedLinks": []
        }
    ]
}