{
    "list": [
        {
            "title": "substack/faucet",
            "url": "https://github.com/substack/faucet",
            "content": "TAP系の出力を見やすく表示するCLI",
            "tags": [
                "node.js",
                "testing"
            ],
            "date": "2014-01-01T03:14:27.201Z",
            "related-links": []
        },
        {
            "title": "Release v0.2.0: 0.2.0 · nzakas/eslint",
            "url": "https://github.com/nzakas/eslint/releases/tag/v0.2.0",
            "content": "eslint 0.2.0リリース。\nルールの追加等",
            "tags": [
                "JavaScript",
                "Tools",
                "ReleaseNote"
            ],
            "date": "2014-01-02T02:26:11.626Z",
            "related-links": [
                {
                    "title": "0.2.0 · 72d0fce · nzakas/eslint",
                    "url": "https://github.com/nzakas/eslint/commit/72d0fce14428716f82f5526a0a3097c50b491e97"
                }
            ]
        },
        {
            "title": "Test-driving a Node.JS API",
            "url": "http://www.jorisooms.be/testing-your-node-api-with-supertest/",
            "content": "supertestを使ったNodeアプリのAPIをテスト駆動開発していくチュートリアル",
            "tags": [
                "node.js",
                "API",
                "testing",
                "tutorial"
            ],
            "date": "2014-01-02T12:43:22.077Z",
            "related-links": [
                {
                    "title": "visionmedia/supertest",
                    "url": "https://github.com/visionmedia/supertest"
                }
            ]
        },
        {
            "title": "YAND - Yet Another Node.js Documentation",
            "url": "http://nodemanja.herokuapp.com/",
            "content": "Node.jsのドキュメントビューアサイト",
            "tags": [
                "node.js",
                "リファレンス",
                "document"
            ],
            "date": "2014-01-03T13:40:29.338Z",
            "related-links": []
        },
        {
            "title": "jQuery Mobile 1.4.0 Released | jQuery Mobile",
            "url": "http://blog.jquerymobile.com/2013/12/23/jquery-mobile-1-4-0-released/",
            "content": "jQuery Mobile 1.4.0リリース。",
            "tags": [
                "jQuery",
                "mobile",
                "ReleaseNote"
            ],
            "date": "2014-01-05T08:12:53.684Z",
            "related-links": []
        },
        {
            "title": "Getting Started With Gulp | Travis Maynard",
            "url": "http://travismaynard.com/writing/getting-started-with-gulp",
            "content": "タスク実行ツールのgulpについての導入方法や設定コードの書き方についてのチュートリアル",
            "tags": [
                "gulp",
                "JavaScript",
                "console",
                "Tools",
                "tutorial"
            ],
            "date": "2014-01-06T05:25:39.613Z",
            "related-links": [
                {
                    "title": "gulp.js - the streaming build system",
                    "url": "http://gulpjs.com/"
                }
            ]
        },
        {
            "title": "Koa 0.2.0 — Code adventures — Medium",
            "url": "https://medium.com/code-adventures/a3a046a04836",
            "content": "NodeのウェブフレームワークKoa 0.2.0リリース。\nSocketのエラーハンドリング、Debug用のComposeモジュールの改善等",
            "tags": [
                "node.js",
                "ReleaseNote"
            ],
            "date": "2014-01-06T12:02:42.370Z",
            "related-links": [
                {
                    "title": "koajs/compose",
                    "url": "https://github.com/koajs/compose"
                }
            ]
        },
        {
            "title": "JavaScript Stringでサロゲートペアを扱う - teppeis blog",
            "url": "http://teppeis.hatenablog.com/entry/2014/01/surrogate-pair-in-javascript",
            "content": "サロゲートペアを考慮した文字数カウント(正規表現、ES6 Iterator)\nコードポイントの取得/文字生成",
            "tags": [
                "JavaScript",
                "firefox"
            ],
            "date": "2014-01-06T12:18:09.412Z",
            "related-links": [
                {
                    "title": "JavaScript has a Unicode problem · Mathias Bynens",
                    "url": "http://mathiasbynens.be/notes/javascript-unicode"
                }
            ]
        },
        {
            "title": "Functional JavaScript for crawling the Web | Code | Nicolas Perriault",
            "url": "https://nicolas.perriault.net/code/2013/functional-javascript-for-crawling-the-web/",
            "content": "FunctionalアプローチでDOMを走査する話。\n関数呼出を重ねすぎると読みにくくなるので、関数合成的なsequence関数を作ったり、ES6の=>やRest Argumentsの利用などを使ってより小さく書くなどしてる。\nそれぞれが関数であるのでテスト等も書きやすい。",
            "tags": [
                "JavaScript",
                "DOM"
            ],
            "date": "2014-01-06T12:51:16.146Z",
            "related-links": [
                {
                    "title": "functional javascript",
                    "url": "http://www.functionaljavascript.com/"
                }
            ]
        },
        {
            "title": "D3 Tips and Tricks by Malcolm Maclean [Leanpub PDF/iPad/Kindle]",
            "url": "https://leanpub.com/D3-Tips-and-Tricks",
            "content": "D3.jsについての書籍\n$0から任意の値段購入できる",
            "tags": [
                "d3.js",
                "book"
            ],
            "date": "2014-01-06T13:11:31.972Z",
            "related-links": []
        },
        {
            "title": "Node Streams for APIs - collect {thoughts}",
            "url": "http://blog.drewolson.org/blog/2014/01/04/node-streams-for-apis",
            "content": "NodeのStreamを使ったAPIの実装について。\nテストの書き方、Streamの実装方法をAPIレンスポンスを返すものを書きながら見ていく話",
            "tags": [
                "node.js"
            ],
            "date": "2014-01-06T13:29:07.090Z",
            "related-links": []
        },
        {
            "title": "Advanced Features in Sinon · Ken Powers",
            "url": "http://www.kenpowers.net/blog/advanced-features-in-sinon/",
            "content": "Sinon.jsのFake Timer、spy、Fake Serversを使ったテストについて。\n",
            "tags": [
                "JavaScript",
                "testing"
            ],
            "date": "2014-01-06T13:34:46.110Z",
            "related-links": []
        }
    ]
}