{
    "list": [
        {
            "date": "2023-11-01T03:57:57.663Z",
            "title": "Remix ❤️ Vite | Remix",
            "url": "https://remix.run/blog/remix-heart-vite",
            "content": "RemixのViteサポートについて。\nRemixがViteのプラグインとして導入できるようになり、Viteの開発サーバやビルド、プラグインの仕組みを使って開発できるようになる。\nまだCloudflareはサポートしていないが、今後サポート予定",
            "tags": [
                "React",
                "Remix",
                "vite",
                "article"
            ],
            "relatedLinks": []
        },
        {
            "date": "2023-11-01T04:32:23.045Z",
            "title": "Release v2.2.0 · remix-run/remix",
            "url": "https://github.com/remix-run/remix/releases/tag/remix%402.2.0",
            "content": "Remix 2.2.0リリース。\nViteのサポート、Fetcherにkeyを指定できるように。\n`future.v3_fetcherPersist`フラグで、Fetcherのクリーンアップの新しい挙動をopt-inできるようになるなど",
            "tags": [
                "Remix",
                "React",
                "JavaScript",
                "library",
                "ReleaseNote"
            ],
            "relatedLinks": [
                {
                    "title": "Remix ❤️ Vite | Remix",
                    "url": "https://remix.run/blog/remix-heart-vite"
                }
            ]
        },
        {
            "date": "2023-11-01T08:17:23.936Z",
            "title": "Release 3.0.0 · facebook/docusaurus",
            "url": "https://github.com/facebook/docusaurus/releases/tag/v3.0.0",
            "content": "docusauru 3.0.0リリース。",
            "tags": [
                "React",
                "document",
                "Tools",
                "ReleaseNote"
            ],
            "relatedLinks": []
        },
        {
            "date": "2023-11-01T22:53:17.416Z",
            "title": "New in Chrome 119 - Chrome for Developers",
            "url": "https://developer.chrome.com/en/blog/new-in-chrome-119/",
            "content": "Chrome 119リリース。\nCookieのExpiresの最大値を400日にする変更を過去分に対して適応、WebSQLの削除。\nCSSの`:user-valid`/`:user-invalid`の擬似クラスのサポート、relative color構文のサポート、clip-pathプロパティの改善など",
            "tags": [
                "Chrome",
                "ReleaseNote"
            ],
            "relatedLinks": []
        },
        {
            "date": "2023-11-01T23:25:26.949Z",
            "title": "WebAssembly Garbage Collection (WasmGC) now enabled by default in Chrome - Chrome for Developers",
            "url": "https://developer.chrome.com/en/blog/wasmgc/",
            "content": "Chrome 119でサポートされたWasmGCについて。\nWasm上に独自のGCを実装せずに、既存のGCを再利用できるようにするHeap管理の仕組みについて",
            "tags": [
                "Chrome",
                "WebAssembly",
                "article"
            ],
            "relatedLinks": []
        },
        {
            "date": "2023-11-03T00:10:14.887Z",
            "title": "Deno 1.38: HTML doc generator and HMR",
            "url": "https://deno.com/blog/v1.38",
            "content": "Deno v1.38リリース。\n`deno doc --html`で静的なHTMLなドキュメントを生成をサポート。\n`--unstable-hmr`でHMRをサポート、`--unstable-byonm`でnpmなどでインストールした`node_modules`のnpmパッケージを利用できるように、`node:*`をサポート。\n`deno run --env`で`.env`のロードをサポート、`std/http`で`EventSource` APIのサポートなど。\nその他には、`http/server`の非推奨化、`std/io`の非推奨化、`std/wasi`の非推奨化などが含まれている。",
            "tags": [
                "deno",
                "ReleaseNote"
            ],
            "relatedLinks": []
        },
        {
            "date": "2023-11-03T01:05:32.024Z",
            "title": "フロントエンドの知識地図—— 一冊でHTML/CSS/JavaScriptの開発技術が学べる本：書籍案内｜技術評論社",
            "url": "https://gihyo.jp/book/2023/978-4-297-13871-4",
            "content": "2023年11月24日発売。\nフロントエンドの入門書",
            "tags": [
                "HTML",
                "CSS",
                "JavaScript",
                "book"
            ],
            "relatedLinks": []
        }
    ]
}
